{
  "generated_at": "2026-03-18T12:18:47.688348+00:00",
  "generated_at_human": "2026-03-18 12:18 UTC",
  "raw_data": {
    "hackernews": {
      "source": "hackernews",
      "category": "tech_ai_nerd",
      "count": 25,
      "items": [
        {
          "title": "Rob Pike's 5 Rules of Programming",
          "url": "https://www.cs.unc.edu/~stotts/COMP590-059-f24/robsrules.html",
          "score": 155,
          "comments": 77
        },
        {
          "title": "JPEG Compression",
          "url": "https://www.sophielwang.com/blog/jpeg",
          "score": 256,
          "comments": 52
        },
        {
          "title": "Measuring progress toward AGI: A cognitive framework",
          "url": "https://blog.google/innovation-and-ai/models-and-research/google-deepmind/measuring-agi-cognitive-framework/",
          "score": 7,
          "comments": 8
        },
        {
          "title": "Write up of my homebrew CPU build",
          "url": "https://willwarren.com/2026/03/12/building-my-own-cpu-part-3-from-simulation-to-hardware/",
          "score": 99,
          "comments": 15
        },
        {
          "title": "Ask HN: What breaks first when your team grows from 10 to 50 people?",
          "url": "https://news.ycombinator.com/item?id=47386284",
          "score": 45,
          "comments": 37
        },
        {
          "title": "Nightingale – open-source karaoke app that works with any song on your computer",
          "url": "https://nightingale.cafe/",
          "score": 99,
          "comments": 12
        },
        {
          "title": "Mistral AI Releases Forge",
          "url": "https://mistral.ai/news/forge",
          "score": 542,
          "comments": 122
        },
        {
          "title": "How the Eon Team Produced a Virtual Embodied Fly",
          "url": "https://eon.systems/updates/embodied-brain-emulation",
          "score": 31,
          "comments": 8
        },
        {
          "title": "A Decade of Slug",
          "url": "https://terathon.com/blog/decade-slug.html",
          "score": 637,
          "comments": 63
        },
        {
          "title": "Celebrating Tony Hoare's mark on computer science",
          "url": "https://bertrandmeyer.com/2026/03/16/celebrating-tony-hoares-mark-on-computer-science/",
          "score": 51,
          "comments": 5
        },
        {
          "title": "Microsoft's 'unhackable' Xbox One has been hacked by 'Bliss'",
          "url": "https://www.tomshardware.com/video-games/console-gaming/microsofts-unhackable-xbox-one-has-been-hacked-by-bliss-the-2013-console-finally-fell-to-voltage-glitching-allowing-the-loading-of-unsigned-code-at-every-level",
          "score": 705,
          "comments": 258
        },
        {
          "title": "Show HN: Pgit – A Git-like CLI backed by PostgreSQL",
          "url": "https://oseifert.ch/blog/building-pgit",
          "score": 61,
          "comments": 24
        },
        {
          "title": "Python 3.15's JIT is now back on track",
          "url": "https://fidget-spinner.github.io/posts/jit-on-track.html",
          "score": 399,
          "comments": 223
        },
        {
          "title": "More than 135 open hardware devices flashable with your own firmware",
          "url": "https://openhardware.directory",
          "score": 257,
          "comments": 30
        },
        {
          "title": "The pleasures of poor product design",
          "url": "https://www.inconspicuous.info/p/the-pleasures-of-poor-product-design",
          "score": 145,
          "comments": 50
        },
        {
          "title": "(Media over QUIC) on a Boat",
          "url": "https://moq.dev/blog/on-a-boat/",
          "score": 31,
          "comments": 3
        },
        {
          "title": "Ndea (YC W26) is hiring a symbolic RL search guidance lead",
          "url": "https://ndea.com/jobs/search-guidance",
          "score": 1,
          "comments": 0
        },
        {
          "title": "Get Shit Done: A meta-prompting, context engineering and spec-driven dev system",
          "url": "https://github.com/gsd-build/get-shit-done",
          "score": 360,
          "comments": 181
        },
        {
          "title": "Show HN: Sub-millisecond VM sandboxes using CoW memory forking",
          "url": "https://github.com/adammiribyan/zeroboot",
          "score": 192,
          "comments": 49
        },
        {
          "title": "Have a fucking website",
          "url": "https://www.otherstrangeness.com/2026/03/14/have-a-fucking-website/",
          "score": 507,
          "comments": 273
        },
        {
          "title": "Judge orders restoration of Voice of America",
          "url": "https://apnews.com/article/voice-of-america-kari-lake-trump-cd6d1ef05272f842705da0ed38d3de24",
          "score": 37,
          "comments": 13
        },
        {
          "title": "Why AI systems don't learn – On autonomous learning from cognitive science",
          "url": "https://arxiv.org/abs/2603.15381",
          "score": 138,
          "comments": 70
        },
        {
          "title": "Unsloth Studio",
          "url": "https://unsloth.ai/docs/new/studio",
          "score": 309,
          "comments": 59
        },
        {
          "title": "A tale about fixing eBPF spinlock issues in the Linux kernel",
          "url": "https://rovarma.com/articles/a-tale-about-fixing-ebpf-spinlock-issues-in-the-linux-kernel/",
          "score": 114,
          "comments": 8
        },
        {
          "title": "Animation 10k Starlink Satellites",
          "url": "https://spaceweather.com/archive.php?view=1&day=18&month=03&year=2026",
          "score": 16,
          "comments": 20
        }
      ]
    },
    "crypto_prices": {
      "source": "coingecko",
      "category": "crypto",
      "count": 5,
      "items": [
        {
          "name": "Bitcoin",
          "symbol": "BTC",
          "price": 72805,
          "change_24h": -1.57,
          "change_7d": 4.59,
          "market_cap": 1455566379251
        },
        {
          "name": "Ethereum",
          "symbol": "ETH",
          "price": 2261.85,
          "change_24h": -2.66,
          "change_7d": 11.49,
          "market_cap": 272623728925
        },
        {
          "name": "Solana",
          "symbol": "SOL",
          "price": 91.79,
          "change_24h": -2.18,
          "change_7d": 7.53,
          "market_cap": 52407114416
        },
        {
          "name": "Dogecoin",
          "symbol": "DOGE",
          "price": 0.096892,
          "change_24h": -3.06,
          "change_7d": 5.07,
          "market_cap": 14856540500
        },
        {
          "name": "Cardano",
          "symbol": "ADA",
          "price": 0.278768,
          "change_24h": -2.74,
          "change_7d": 7.69,
          "market_cap": 10257759154
        }
      ]
    },
    "crypto_trending": {
      "source": "coingecko_trending",
      "category": "crypto",
      "count": 10,
      "items": [
        {
          "name": "Kaspa",
          "symbol": "KAS",
          "market_cap_rank": 68
        },
        {
          "name": "Hyperliquid",
          "symbol": "HYPE",
          "market_cap_rank": 14
        },
        {
          "name": "Bitcoin",
          "symbol": "BTC",
          "market_cap_rank": 1
        },
        {
          "name": "LayerZero",
          "symbol": "ZRO",
          "market_cap_rank": 107
        },
        {
          "name": "Monad",
          "symbol": "MON",
          "market_cap_rank": 151
        },
        {
          "name": "Pudgy Penguins",
          "symbol": "PENGU",
          "market_cap_rank": 103
        },
        {
          "name": "Bittensor",
          "symbol": "TAO",
          "market_cap_rank": 39
        },
        {
          "name": "Aster",
          "symbol": "ASTER",
          "market_cap_rank": 49
        },
        {
          "name": "Solana",
          "symbol": "SOL",
          "market_cap_rank": 7
        },
        {
          "name": "pippin",
          "symbol": "PIPPIN",
          "market_cap_rank": 254
        }
      ]
    },
    "macro_markets": {
      "source": "perplexity",
      "category": "macro_stocks",
      "query": "What are the most important macroeconomic and stock market news and developments from the past 24 hours? Include major index movements, Fed/central bank news, and significant company earnings or announcements.",
      "recency_filter": "day",
      "count": 5,
      "items": [
        {
          "title": "Nasdaq Climbs Over 100 Points Despite Extreme Fear Index",
          "summary": "The Nasdaq Composite rose over 100 points on Tuesday amid high investor anxiety, with the Fear and Greed Index at 21.5 in 'Extreme Fear' zone. Markets await Federal Reserve's two-day policy meeting outcome, likely keeping rates near 3.75%, and upcoming PPI data.",
          "source": "Gotrade News / Bloomberg / Benzinga",
          "url": "https://www.heygotrade.com/en/news/nasdaq-dominates-despite-high-fear-index"
        },
        {
          "title": "S&P 500 Sectors Mixed; Energy and Consumer Discretionary Lead Gains",
          "summary": "Most S&P 500 sectors ended positively on Tuesday, driven by gains in energy, consumer discretionary, and communication services, while consumer staples and healthcare declined. Focus remains on Fed Chair Powell's statement on inflation and oil prices.",
          "source": "Gotrade News / Benzinga",
          "url": "https://www.heygotrade.com/en/news/nasdaq-dominates-despite-high-fear-index"
        },
        {
          "title": "Brent Crude Falls Over 2% on Iraq-Turkey Oil Export Reopening",
          "summary": "Brent crude prices dropped more than 2% after Iraq reopened oil exports through Turkey's Ceyhan port, easing supply concerns from Iran conflict. This occurred despite ongoing market focus on Fed decisions.",
          "source": "Gotrade News",
          "url": "https://www.heygotrade.com/en/news/nasdaq-dominates-despite-high-fear-index"
        },
        {
          "title": "Gold Steady Near $5,000 as Investors Eye Fed Rate-Cut Path",
          "summary": "Gold prices held steady around $5,000 per ounce as investors assess the Federal Reserve's potential rate-cut trajectory ahead of the policy meeting conclusion.",
          "source": "Bloomberg",
          "url": "https://www.heygotrade.com/en/news/nasdaq-dominates-despite-high-fear-index"
        },
        {
          "title": "U.S. Stock Futures Rise Ahead of Fed Interest Rate Decision",
          "summary": "Futures on Nasdaq 100, S&P 500, and Dow Jones were up 0.62%, 0.48%, and 0.52% respectively early Wednesday as markets anticipate the Fed's rate decision and Powell's comments.",
          "source": "TipRanks",
          "url": "https://www.tipranks.com/news/stock-market-news-today-3-18-26-u-s-stock-futures-rise-as-feds-interest-rate-decision-looms"
        }
      ],
      "citations": [
        "https://www.heygotrade.com/en/news/nasdaq-dominates-despite-high-fear-index",
        "https://robinhood.com/us/en/prediction-markets/financial/events/sp-500-futures-price-on-march-18-2026-mar-18-2026/",
        "https://www.tipranks.com/news/stock-market-news-today-3-18-26-u-s-stock-futures-rise-as-feds-interest-rate-decision-looms"
      ]
    },
    "crypto_news": {
      "source": "perplexity",
      "category": "crypto_news",
      "query": "What are the most significant cryptocurrency and blockchain news from the past 24 hours? Include major price movements, regulatory news, and notable project developments.",
      "recency_filter": "day",
      "count": 8,
      "items": [
        {
          "title": "Bitcoin Trades Near $73,500–$73,900 Amid FOMC Anticipation and Institutional Inflows",
          "summary": "Bitcoin is holding strong at $73,500–$73,900, approaching $75,000 resistance ahead of the FOMC rate decision, supported by $1.1 billion in recent U.S. spot ETF inflows and MicroStrategy's ongoing accumulation strategy.",
          "source": "Phemex",
          "url": "https://phemex.com/blogs/bitcoin-outperforming-gold-stocks-dollar-iran-war-march-18"
        },
        {
          "title": "Aster Chain Launches Privacy-Focused Mainnet with Zero-Knowledge Encryption",
          "summary": "Aster, backed by YZi Labs, has launched its Layer-1 blockchain mainnet featuring stealth addresses to prevent front-running, with the ASTER token rallying over 5% to $0.76 and cross-chain support from Ethereum and Solana.",
          "source": "FameEX",
          "url": "https://www.fameex.com/en-US/news/crypto-news-recap-20260318"
        },
        {
          "title": "SEC and CFTC Clarify Most Crypto Assets Are Not Securities, Define Staking and Airdrops",
          "summary": "U.S. regulators SEC and CFTC have issued clarifications stating most crypto assets are not securities and provided definitions for staking, airdrops, and contracts, potentially easing regulatory uncertainty.",
          "source": "BitDigest",
          "url": "https://bitdigest.substack.com/p/wednesday-march-18-2026"
        },
        {
          "title": "MicroStrategy Adds 22,337 BTC, Total Holdings Reach 761,068 BTC",
          "summary": "MicroStrategy raised $1.18 billion via preferred stock and acquired 22,337 more Bitcoin, bringing its total holdings to 761,068 BTC amid continued corporate accumulation trends.",
          "source": "BitDigest",
          "url": "https://bitdigest.substack.com/p/wednesday-march-18-2026"
        },
        {
          "title": "GSR Acquires Autonomous and Architech for $57 Million",
          "summary": "Crypto trading firm GSR has acquired Autonomous and Architech for $57 million to bolster its infrastructure capabilities in the blockchain space.",
          "source": "BitDigest",
          "url": "https://bitdigest.substack.com/p/wednesday-march-18-2026"
        },
        {
          "title": "Moody's Launches On-Chain Credit Ratings",
          "summary": "Moody's has introduced on-chain credit rating services, marking a significant step in integrating traditional credit assessments with blockchain technology.",
          "source": "BitDigest",
          "url": "https://bitdigest.substack.com/p/wednesday-march-18-2026"
        },
        {
          "title": "PayPal Expands Stablecoins to 68 Additional Countries",
          "summary": "PayPal is rolling out its stablecoin services to 68 more countries, enhancing global access to crypto payments and stable value transfers.",
          "source": "BitDigest",
          "url": "https://bitdigest.substack.com/p/wednesday-march-18-2026"
        },
        {
          "title": "Ethereum Trades Near $2,315 with Neutral Funding Rates",
          "summary": "Ethereum is stable at around $2,315 as funding rates normalize post-leverage flush, though a drop below $2,206 risks $1.156 billion in liquidations.",
          "source": "FameEX",
          "url": "https://www.fameex.com/en-US/news/crypto-news-recap-20260318"
        }
      ],
      "citations": [
        "https://sergeytereshkin.com/publications/cryptocurrency-news-march-18-2026-bitcoin-ethereum-institutional-investments",
        "https://www.fameex.com/en-US/news/crypto-news-recap-20260318",
        "https://bitdigest.substack.com/p/wednesday-march-18-2026",
        "https://phemex.com/blogs/bitcoin-outperforming-gold-stocks-dollar-iran-war-march-18"
      ]
    },
    "ai_news": {
      "source": "perplexity",
      "category": "ai",
      "query": "What are the most important artificial intelligence and machine learning news and developments from the past 24 hours? Include new model releases, company announcements, research breakthroughs, and industry trends.",
      "recency_filter": "day",
      "count": 5,
      "items": [
        {
          "title": "Multiverse Computing and Axelera AI Announce Strategic Collaboration for Edge AI Models",
          "summary": "Multiverse Computing and Axelera AI have launched a technology collaboration to integrate compressed AI models into Axelera’s Metis and Europa edge platforms, enabling efficient AI inference on low-power devices for applications in industrial, retail, mobility, and more.",
          "source": "The Quantum Insider",
          "url": "https://thequantuminsider.com/2026/03/18/ultiverse-computing-axelera-ai-strategic-collaboration-ai-models-edge-devices/"
        },
        {
          "title": "NCS Partners with NVIDIA to Deploy Sovereign Agentic AI for Enterprises",
          "summary": "NCS, a Singtel subsidiary, has partnered with NVIDIA to deploy sovereign agentic AI solutions that allow enterprises to run AI agents on-premises or in the cloud while maintaining data security and governance for uses like service desks, video systems, and logistics.",
          "source": "Technode Global",
          "url": "https://technode.global/2026/03/18/ncs-partners-nvidia-to-deploy-sovereign-agentic-ai-for-enterprises/"
        },
        {
          "title": "TCS and Pearson Partner to Accelerate AI-Powered Learning for Enterprises",
          "summary": "Tata Consultancy Services (TCS) and Pearson have announced a multi-year partnership to co-develop AI-enabled learning and assessment products, helping enterprises upskill workforces for AI-driven changes using contextual AI and digital platforms.",
          "source": "PR Newswire",
          "url": "https://www.prnewswire.com/news-releases/tcs-and-pearson-partner-to-accelerate-ai-powered-learning-for-global-industries-302716317.html"
        },
        {
          "title": "Embedded AI Market Projected to Reach USD 42.3 Billion by 2033",
          "summary": "The embedded AI market, valued at USD 13.8 billion in 2026, is expected to grow to USD 42.3 billion by 2033 at a 17.3% CAGR, driven by advancements in AI chipsets, NPUs, and edge deployment for real-time processing in IoT, robotics, and smart devices.",
          "source": "GlobeNewswire",
          "url": "https://www.globenewswire.com/news-release/2026/03/18/3257964/0/en/Embedded-AI-Market-Accelerates-with-Advancements-in-Semiconductor-Design-and-Edge-Based-AI-Deployment-Valued-at-USD-42-3-billion-by-2033.html"
        },
        {
          "title": "AI in Sports Market Forecast: Machine Learning to Dominate by 2030",
          "summary": "The AI in sports market is expanding with machine learning projected to hold 35% share by 2030, supported by performance analytics, injury prevention, and integrations with IoT and AR/VR for enhanced training and fan engagement.",
          "source": "National Law Review",
          "url": "https://natlawreview.com/press-releases/ai-sports-market-2026-data-analytics-and-performance-intelligence"
        }
      ],
      "citations": [
        "https://natlawreview.com/press-releases/ai-sports-market-2026-data-analytics-and-performance-intelligence",
        "https://thequantuminsider.com/2026/03/18/ultiverse-computing-axelera-ai-strategic-collaboration-ai-models-edge-devices/",
        "https://www.globenewswire.com/news-release/2026/03/18/3257964/0/en/Embedded-AI-Market-Accelerates-with-Advancements-in-Semiconductor-Design-and-Edge-Based-AI-Deployment-Valued-at-USD-42-3-billion-by-2033.html",
        "https://technode.global/2026/03/18/ncs-partners-nvidia-to-deploy-sovereign-agentic-ai-for-enterprises/",
        "https://www.prnewswire.com/news-releases/tcs-and-pearson-partner-to-accelerate-ai-powered-learning-for-global-industries-302716317.html",
        "https://www.bcg.com/publications/2026/how-ai-can-help-universities-capture-opportunity"
      ]
    },
    "gaming": {
      "source": "perplexity",
      "category": "gaming",
      "query": "What are the most notable video game and gaming industry news from the past 24 hours? Include game releases, announcements, esports, and industry developments.",
      "recency_filter": "day",
      "count": 3,
      "items": [
        {
          "title": "Xbox Game Pass Adds 12 New Titles in March 2026 Wave 2 Including South of Midnight Today",
          "summary": "Xbox Game Pass is adding 12 new PC and Xbox titles as part of its March 2026 Wave 2, with South of Midnight launching on Cloud, Console, Handheld, and PC today, March 18. Upcoming additions include Clair Obscur: Expedition 33 on April 2, along with updates for Valorant and Sea of Thieves Season 19.",
          "source": "Worthplaying",
          "url": "https://worthplaying.com/article/2026/3/17/news/149340-xbox-game-pass-reveals-12-new-pcxbox-titles-being-added-in-march-2026-as-part-of-wave-2/"
        },
        {
          "title": "Xbox Game Pass Announces Late March and April 2026 Additions",
          "summary": "Xbox has revealed additional games joining Game Pass for the end of March and into April 2026, expanding options for subscribers with new releases and updates.",
          "source": "Gamer Social Club",
          "url": "https://gamersocialclub.ca/2026/03/17/xbox-game-pass-additions-announced-for-end-of-march-2026/"
        },
        {
          "title": "Sony Releases Surprise PS3 System Update 4.93",
          "summary": "Sony deployed PS3 system software update 4.93 on March 18, 2026, marking the first update in exactly one year for the legacy console.",
          "source": "PlayStation Lifestyle",
          "url": "https://www.playstationlifestyle.net/2026/03/18/ps3-system-update-4-93-march-2026/amp/"
        }
      ],
      "citations": [
        "https://worthplaying.com/article/2026/3/17/news/149340-xbox-game-pass-reveals-12-new-pcxbox-titles-being-added-in-march-2026-as-part-of-wave-2/",
        "https://explorminate.org/fortnightly-4x-and-tactics-news-roundup-march-1st-to-march-17th/",
        "https://gamersocialclub.ca/2026/03/17/xbox-game-pass-additions-announced-for-end-of-march-2026/",
        "https://www.playstationlifestyle.net/2026/03/18/ps3-system-update-4-93-march-2026/amp/"
      ]
    },
    "tech_news": {
      "source": "perplexity",
      "category": "tech",
      "query": "What are the most important technology news and developments from the past 24 hours? Include major product launches, company news, and significant tech industry developments. Exclude AI-specific news.",
      "recency_filter": "day",
      "count": 4,
      "items": [
        {
          "title": "China's Alibaba and Baidu Raise AI Service Prices Amid Surging Demand",
          "summary": "Alibaba plans to increase prices for its T-head AI computing chips by 5-34% and storage by 30%, while Baidu will hike AI cloud product prices by up to 30%, effective April 18, due to global demand and supply chain costs.",
          "source": "Morningstar / Dow Jones Newswires",
          "url": "https://www.morningstar.com/news/dow-jones/202603182039/chinas-big-tech-firms-raise-ai-prices-as-demand-soars"
        },
        {
          "title": "Major Tech Layoffs Hit Meta, Amazon, Atlassian, and Others in 2026",
          "summary": "Companies including Amazon (16,000 jobs), Atlassian (1,600 jobs), Meta (up to 15,000), and Oracle (20,000-30,000) are cutting jobs to pivot toward efficiency and AI infrastructure investments.",
          "source": "Times of India",
          "url": "https://timesofindia.indiatimes.com/technology/tech-news/tech-layoffs-meta-amazon-and-other-companies-cutting-jobs-in-2026/articleshow/129653267.cms"
        },
        {
          "title": "LG Energy Solution Bolsters Leadership in Robotics Battery Market",
          "summary": "LG Energy Solution is supplying high-energy-density cylindrical batteries and immersion cooling tech to over six major robotics firms, positioning itself for growth as the humanoid robot market surges toward 1.53 million units by 2030.",
          "source": "LG Energy Solution News",
          "url": "https://news.lgensol.com/company-news/supplementary-stories/4778/"
        },
        {
          "title": "One-Third of Organizations Lack Data Foundations Despite HR Tech Investments",
          "summary": "Rising investments in HR technology have not resolved data gaps, leaving one-third of organizations without reliable workforce analytics for decision-making.",
          "source": "Las Vegas Sun",
          "url": "https://lasvegassun.com/news/2026/mar/18/despite-rising-hr-tech-investment-one-third-of-org/"
        }
      ],
      "citations": [
        "https://www.heygotrade.com/en/news/google-ai-expansion-challenges-microsoft-apple",
        "https://www.morningstar.com/news/dow-jones/202603182039/chinas-big-tech-firms-raise-ai-prices-as-demand-soars",
        "https://timesofindia.indiatimes.com/technology/tech-news/tech-layoffs-meta-amazon-and-other-companies-cutting-jobs-in-2026/articleshow/129653267.cms",
        "https://news.lgensol.com/company-news/supplementary-stories/4778/",
        "https://lasvegassun.com/news/2026/mar/18/despite-rising-hr-tech-investment-one-third-of-org/"
      ]
    }
  }
}